[
    {
      "short_description": "Clear BGP sessions on a Cisco router",
      "reason": "",
      "close_code": "Successful",
      "closed_at": "2015-07-06 11:56:23",
      "backout_plan": "Due to the limited number of commands in the implementation plan it is not possible to backout the change.\r\n\r\nIf required you are authorized to reboot the router if BGP fails to work",
      "impact": "3 - Low",
      "description": "Resend the complete BGP table to neighboring routers\r\n\r\n--Both neighbors need to support soft reset route refresh capability.\r\n--Stores complete BGP table of you neighbor in router memory.\r\n--Not a good idea on a peering router with full feed, due to the memory requirements.\r\n",
      "business_service": "",
      "type": "Standard",
      "close_notes": "Completed without issues",
      "sys_id": "1766f1de47410200e90d87e8dee490f6",
      "number": "CHG0000024",
      "opened_at": "2015-06-09 11:55:46",
      "sys_domain": "global",
      "state": "Closed",
      "justification": "",
      "sys_created_by": "admin",
      "assigned_to": ""
    },
    {
      "short_description": "Roll back Windows SP2 patch",
      "reason": "",
      "close_code": "",
      "closed_at": "2023-07-20 02:46:15",
      "backout_plan": "",
      "impact": "3 - Low",
      "description": "Please roll-back SP2 patch for all XP Users.\n        ",
      "business_service": "",
      "type": "Normal",
      "close_notes": "",
      "sys_id": "46e9b4afa9fe198101026e122b85f442",
      "number": "CHG0000003",
      "opened_at": "2022-11-10 15:47:34",
      "sys_domain": "global",
      "state": "Closed",
      "justification": "",
      "sys_created_by": "admin",
      "assigned_to": "ITIL User"
    },
    {
      "short_description": "Add network switch to cabinet",
      "reason": "",
      "close_code": "Successful",
      "closed_at": "2015-07-06 12:12:52",
      "backout_plan": "-- Physically remove switch and all associated cabling\r\n-- Remove switch from management, monitoring and ServiceNow CMDB",
      "impact": "3 - Low",
      "description": "This standard change template describes adding a new network switch to a datacenter cabinet",
      "business_service": "",
      "type": "Standard",
      "close_notes": "Implemented",
      "sys_id": "543a39de47410200e90d87e8dee4908a",
      "number": "CHG0000027",
      "opened_at": "2015-07-06 12:12:13",
      "sys_domain": "global",
      "state": "Closed",
      "justification": "",
      "sys_created_by": "admin",
      "assigned_to": ""
    },
    {
      "short_description": "Change VLAN on a Cisco switchport",
      "reason": "",
      "close_code": "Successful",
      "closed_at": "2015-07-06 07:22:05",
      "backout_plan": "Check the previous version of the switchport config in the configuration management database and revert",
      "impact": "3 - Low",
      "description": "Change the port of a Cisco switch to a new VLAN. This would commonly occur when moving a server from one IP network to another.",
      "business_service": "",
      "type": "Standard",
      "close_notes": "Closed successfully",
      "sys_id": "5d77b8da47410200e90d87e8dee49040",
      "number": "CHG0000022",
      "opened_at": "2015-07-06 07:20:38",
      "sys_domain": "global",
      "state": "Closed",
      "justification": "",
      "sys_created_by": "admin",
      "assigned_to": ""
    },
    {
      "short_description": "Decommission server",
      "reason": "",
      "close_code": "Successful",
      "closed_at": "2015-07-06 11:18:53",
      "backout_plan": "Due to the nature of this procedure any means to back out of this after the process has begun should not be implemented. Any type of recovery from backup or any other tool could cause corruption to the Active Directory database and could cause more harm than good. Once the implementation plan has been started it will need to be carried out completely.",
      "impact": "3 - Low",
      "description": "Decommission a server from use including removal from backup, systems management and monitoring systems and disposal of hardware",
      "business_service": "",
      "type": "Standard",
      "close_notes": "Completed successfully",
      "sys_id": "70ad699e47410200e90d87e8dee4907d",
      "number": "CHG0000023",
      "opened_at": "2015-07-06 11:17:21",
      "sys_domain": "global",
      "state": "Closed",
      "justification": "",
      "sys_created_by": "admin",
      "assigned_to": ""
    },
    {
      "short_description": "Clear BGP sessions on a Cisco router",
      "reason": "",
      "close_code": "Successful",
      "closed_at": "2015-07-06 12:00:51",
      "backout_plan": "Due to the limited number of commands in the implementation plan it is not possible to backout the change.\r\n\r\nIf required you are authorized to reboot the router if BGP fails to work",
      "impact": "3 - Low",
      "description": "Resend the complete BGP table to neighboring routers\r\n\r\n--Both neighbors need to support soft reset route refresh capability.\r\n--Stores complete BGP table of you neighbor in router memory.\r\n--Not a good idea on a peering router with full feed, due to the memory requirements.\r\n",
      "business_service": "",
      "type": "Standard",
      "close_notes": "Worked",
      "sys_id": "7b77f5de47410200e90d87e8dee490b8",
      "number": "CHG0000026",
      "opened_at": "2015-07-06 12:00:26",
      "sys_domain": "global",
      "state": "Closed",
      "justification": "",
      "sys_created_by": "admin",
      "assigned_to": ""
    },
    {
      "short_description": "Reboot Windows Server",
      "reason": "",
      "close_code": "Successful",
      "closed_at": "2015-07-06 12:30:01",
      "backout_plan": "There is no backout plan for this change template",
      "impact": "3 - Low",
      "description": "Reboot a Windows Server (after patching or to clear a fault) making sure that it is removed from monitoring alerts, that network attached storage is unmounted and that it restarts cleanly",
      "business_service": "",
      "type": "Standard",
      "close_notes": "Server rebooted",
      "sys_id": "892eb11247810200e90d87e8dee4908f",
      "number": "CHG0000028",
      "opened_at": "2015-07-06 12:29:28",
      "sys_domain": "global",
      "state": "Closed",
      "justification": "",
      "sys_created_by": "admin",
      "assigned_to": ""
    },
    {
      "short_description": "Switch Sales over to the new 555 prefix\n        ",
      "reason": "",
      "close_code": "",
      "closed_at": "2023-07-20 02:46:18",
      "backout_plan": "",
      "impact": "3 - Low",
      "description": "Sales has their own private dialing prefix now so they'll\n            always have an open outside line even if the PBX is full.\n        ",
      "business_service": "",
      "type": "Normal",
      "close_notes": "",
      "sys_id": "9d41c061c611228700edc88b231ec47c",
      "number": "CHG0000002",
      "opened_at": "2021-05-29 15:40:25",
      "sys_domain": "global",
      "state": "Canceled",
      "justification": "",
      "sys_created_by": "pat",
      "assigned_to": "ITIL User"
    },
    {
      "short_description": "Change VLAN on a Cisco switchport",
      "reason": "",
      "close_code": "Successful",
      "closed_at": "2015-07-03 07:18:32",
      "backout_plan": "Check the previous version of the switchport config in the configuration management database and revert",
      "impact": "3 - Low",
      "description": "Change the port of a Cisco switch to a new VLAN. This would commonly occur when moving a server from one IP network to another.",
      "business_service": "",
      "type": "Standard",
      "close_notes": "Change completed successfully",
      "sys_id": "aa0ad55147810200e90d87e8dee490e1",
      "number": "CHG0000021",
      "opened_at": "2015-07-03 07:17:49",
      "sys_domain": "global",
      "state": "Closed",
      "justification": "",
      "sys_created_by": "admin",
      "assigned_to": "Bow Ruggeri"
    },
    {
      "short_description": "Change VLAN on a Cisco switchport",
      "reason": "",
      "close_code": "Unsuccessful",
      "closed_at": "2015-07-03 07:40:14",
      "backout_plan": "Check the previous version of the switchport config in the configuration management database and revert",
      "impact": "3 - Low",
      "description": "Change the port of a Cisco switch to a new VLAN. This would commonly occur when moving a server from one IP network to another.",
      "business_service": "",
      "type": "Standard",
      "close_notes": "The switch crashed whilst applying this change.",
      "sys_id": "b0e8555147810200e90d87e8dee4902c",
      "number": "CHG0000020",
      "opened_at": "2015-07-03 07:12:47",
      "sys_domain": "global",
      "state": "Closed",
      "justification": "",
      "sys_created_by": "don.goodliffe",
      "assigned_to": ""
    },
    {
      "short_description": "Clear BGP sessions on a Cisco router",
      "reason": "",
      "close_code": "Successful",
      "closed_at": "2015-07-06 11:58:27",
      "backout_plan": "Due to the limited number of commands in the implementation plan it is not possible to backout the change.\r\n\r\nIf required you are authorized to reboot the router if BGP fails to work",
      "impact": "3 - Low",
      "description": "Resend the complete BGP table to neighboring routers\r\n\r\n--Both neighbors need to support soft reset route refresh capability.\r\n--Stores complete BGP table of you neighbor in router memory.\r\n--Not a good idea on a peering router with full feed, due to the memory requirements.\r\n",
      "business_service": "",
      "type": "Standard",
      "close_notes": "No issues",
      "sys_id": "b4f675de47410200e90d87e8dee490cc",
      "number": "CHG0000025",
      "opened_at": "2015-07-06 11:58:03",
      "sys_domain": "global",
      "state": "Closed",
      "justification": "",
      "sys_created_by": "admin",
      "assigned_to": ""
    },
    {
      "short_description": "Please reboot ApplicationServerHelpdesk",
      "reason": "broken",
      "close_code": "",
      "closed_at": "",
      "backout_plan": "",
      "impact": "3 - Low",
      "description": "",
      "business_service": "",
      "type": "Emergency",
      "close_notes": "",
      "sys_id": "0126961347c12200e0ef563dbb9a717e",
      "number": "CHG0040003",
      "opened_at": "2016-08-10 09:10:41",
      "sys_domain": "global",
      "state": "New",
      "justification": "",
      "sys_created_by": "admin",
      "assigned_to": ""
    },
    {
      "short_description": "Oct 23",
      "reason": "",
      "close_code": "Successful",
      "closed_at": "",
      "backout_plan": "",
      "impact": "3 - Low",
      "description": "",
      "business_service": "",
      "type": "Emergency",
      "close_notes": "Successfully closed",
      "sys_id": "0204967997023110de1dfa67f053afc8",
      "number": "CHG0030011",
      "opened_at": "2023-10-23 08:38:14",
      "sys_domain": "global",
      "state": "New",
      "justification": "",
      "sys_created_by": "abel.tuter",
      "assigned_to": ""
    },
    {
      "short_description": "Change default router on unix201",
      "reason": "",
      "close_code": "",
      "closed_at": "",
      "backout_plan": "revert to default gateway 192.168.1.100\nRestart network with /etc/init.d/network restart\ntest network connectivity using ping 192.168.1.254\ntest network connectivity using ping 10.10.100.10",
      "impact": "3 - Low",
      "description": "",
      "business_service": "",
      "type": "Normal",
      "close_notes": "",
      "sys_id": "02cd7552db252200a6a2b31be0b8f5e0",
      "number": "CHG0000076",
      "opened_at": "2023-07-22 01:21:35",
      "sys_domain": "global",
      "state": "Authorize",
      "justification": "",
      "sys_created_by": "admin",
      "assigned_to": "David Loo"
    },
    {
      "short_description": "SGHUNG Dec 5",
      "reason": "",
      "close_code": "Unsuccessful",
      "closed_at": "",
      "backout_plan": "",
      "impact": "3 - Low",
      "description": "",
      "business_service": "",
      "type": "Emergency",
      "close_notes": "Bad",
      "sys_id": "05cd307f97323110de1dfa67f053af33",
      "number": "CHG0030024",
      "opened_at": "2023-12-05 13:16:16",
      "sys_domain": "global",
      "state": "New",
      "justification": "",
      "sys_created_by": "abel.tuter",
      "assigned_to": ""
    },
    {
      "short_description": "Update /etc/network/interfaces to include name servers 8.8.8.8 & 8.8.4.4",
      "reason": "",
      "close_code": "",
      "closed_at": "",
      "backout_plan": "Comment out new line in /etc/network/interfaces",
      "impact": "2 - Medium",
      "description": "We need to add additional redundant name servers to lnux100, lnux101 and PS LinuxApp01",
      "business_service": "",
      "type": "Normal",
      "close_notes": "",
      "sys_id": "06cdb552db252200a6a2b31be0b8f53e",
      "number": "CHG0000081",
      "opened_at": "2023-07-22 01:21:36",
      "sys_domain": "global",
      "state": "Authorize",
      "justification": "",
      "sys_created_by": "admin",
      "assigned_to": "Bow Ruggeri"
    },
    {
      "short_description": "nov 29",
      "reason": "",
      "close_code": "",
      "closed_at": "",
      "backout_plan": "",
      "impact": "3 - Low",
      "description": "",
      "business_service": "",
      "type": "Normal",
      "close_notes": "",
      "sys_id": "085cd5f997323110de1dfa67f053af75",
      "number": "CHG0030017",
      "opened_at": "2023-11-29 10:21:53",
      "sys_domain": "global",
      "state": "New",
      "justification": "",
      "sys_created_by": "abel.tuter",
      "assigned_to": ""
    },
    {
      "short_description": "Deploy new Cisco Catalyst 4500",
      "reason": "",
      "close_code": "",
      "closed_at": "",
      "backout_plan": "Power down switch\nReprovision existing Cisco 2900 switch\nValidate connectivity from all private networks",
      "impact": "2 - Medium",
      "description": "The existing Cisco 2900 is being decommissioned and replaced with a Cisco 4500 that supports additional services and is still supported by Cisco.",
      "business_service": "",
      "type": "Normal",
      "close_notes": "",
      "sys_id": "0dcdb152db252200a6a2b31be0b8f54f",
      "number": "CHG0000039",
      "opened_at": "2023-07-22 01:21:31",
      "sys_domain": "global",
      "state": "Authorize",
      "justification": "",
      "sys_created_by": "admin",
      "assigned_to": "David Loo"
    },
    {
      "short_description": "Update /etc/network/interfaces to include name servers 8.8.8.8 & 8.8.4.4",
      "reason": "",
      "close_code": "",
      "closed_at": "",
      "backout_plan": "Comment out new line in /etc/network/interfaces",
      "impact": "2 - Medium",
      "description": "We need to add additional redundant name servers to lnux100, lnux101 and PS LinuxApp01",
      "business_service": "",
      "type": "Normal",
      "close_notes": "",
      "sys_id": "0dcdb152db252200a6a2b31be0b8f58f",
      "number": "CHG0000043",
      "opened_at": "2023-07-22 01:21:32",
      "sys_domain": "global",
      "state": "Authorize",
      "justification": "",
      "sys_created_by": "admin",
      "assigned_to": "Bow Ruggeri"
    },
    {
      "short_description": "Perform maintenance on database server - bond_trading_uk",
      "reason": "",
      "close_code": "",
      "closed_at": "",
      "backout_plan": "",
      "impact": "3 - Low",
      "description": "",
      "business_service": "",
      "type": "Normal",
      "close_notes": "",
      "sys_id": "0e01e67737310200f212cc028e41f1a8",
      "number": "CHG0000036",
      "opened_at": "2015-08-17 13:39:53",
      "sys_domain": "global",
      "state": "New",
      "justification": "",
      "sys_created_by": "admin",
      "assigned_to": ""
    },
    {
      "short_description": "A failed RAID controller card needs to be replaced on PSORA1",
      "reason": "",
      "close_code": "",
      "closed_at": "",
      "backout_plan": "",
      "impact": "2 - Medium",
      "description": "01:00.0 RAID bus controller: Adaptec AAC-RAID has failed on PSORA1 and needs to be replaced immediately.",
      "business_service": "",
      "type": "Normal",
      "close_notes": "",
      "sys_id": "0ecd7552db252200a6a2b31be0b8f5e6",
      "number": "CHG0000077",
      "opened_at": "2023-07-22 01:21:35",
      "sys_domain": "global",
      "state": "Authorize",
      "justification": "",
      "sys_created_by": "admin",
      "assigned_to": "David Loo"
    },
    {
      "short_description": "Update default support group on all Oracle CI's to Database group",
      "reason": "",
      "close_code": "",
      "closed_at": "",
      "backout_plan": "",
      "impact": "3 - Low",
      "description": "The default support group for all Oracle CI's is being transitioned to the Database group",
      "business_service": "",
      "type": "Normal",
      "close_notes": "",
      "sys_id": "0ecdb552db252200a6a2b31be0b8f537",
      "number": "CHG0000080",
      "opened_at": "2023-07-22 01:21:36",
      "sys_domain": "global",
      "state": "Authorize",
      "justification": "Database group taking over all \nOracle database support activities",
      "sys_created_by": "admin",
      "assigned_to": "Bow Ruggeri"
    },
    {
      "short_description": "Upgrade OWA-SD-01 to MS Windows Server 2016",
      "reason": "",
      "close_code": "",
      "closed_at": "",
      "backout_plan": "re-image OWA-SD-01\nVerify network connectivity\nValidate OWA access using owa_test1 and owa_test2 test users\nFail from DR system back to OWA-SD-01",
      "impact": "2 - Medium",
      "description": "",
      "business_service": "",
      "type": "Normal",
      "close_notes": "",
      "sys_id": "12cdb552db252200a6a2b31be0b8f58a",
      "number": "CHG0000085",
      "opened_at": "2023-07-22 01:21:36",
      "sys_domain": "global",
      "state": "Authorize",
      "justification": "",
      "sys_created_by": "admin",
      "assigned_to": "David Loo"
    },
    {
      "short_description": "Scheduled maintenance on database server - bond_trading_uk",
      "reason": "",
      "close_code": "",
      "closed_at": "",
      "backout_plan": "",
      "impact": "3 - Low",
      "description": "",
      "business_service": "",
      "type": "Normal",
      "close_notes": "",
      "sys_id": "12ffff7137310200f212cc028e41f175",
      "number": "CHG0000034",
      "opened_at": "2015-08-11 15:26:51",
      "sys_domain": "global",
      "state": "New",
      "justification": "",
      "sys_created_by": "admin",
      "assigned_to": ""
    },
    {
      "short_description": "",
      "reason": "",
      "close_code": "",
      "closed_at": "",
      "backout_plan": "",
      "impact": "3 - Low",
      "description": "",
      "business_service": "",
      "type": "Normal",
      "close_notes": "",
      "sys_id": "1719c48197513110de1dfa67f053aff6",
      "number": "CHG0030006",
      "opened_at": "2023-09-13 07:48:45",
      "sys_domain": "global",
      "state": "New",
      "justification": "",
      "sys_created_by": "admin",
      "assigned_to": ""
    },
    {
      "short_description": "Increase db_block_buffers from 5000 to 7500",
      "reason": "",
      "close_code": "",
      "closed_at": "",
      "backout_plan": "rollback to existing db_block_buffer setting",
      "impact": "2 - Medium",
      "description": "The database size has increased and the cache hit rate is at the low end of an acceptable rate. The Database team needss to increase the amount of memory allocated to the Oracle SGA to increase the cache hit rate.",
      "business_service": "",
      "type": "Normal",
      "close_notes": "",
      "sys_id": "1acdb552db252200a6a2b31be0b8f583",
      "number": "CHG0000084",
      "opened_at": "2023-07-22 01:21:36",
      "sys_domain": "global",
      "state": "Authorize",
      "justification": "",
      "sys_created_by": "admin",
      "assigned_to": "David Loo"
    },
    {
      "short_description": "Add network switch to cabinet",
      "reason": "",
      "close_code": "",
      "closed_at": "",
      "backout_plan": "-- Physically remove switch and all associated cabling\n-- Remove switch from management, monitoring and ServiceNow CMDB",
      "impact": "3 - Low",
      "description": "This standard change template describes adding a new network switch to a datacenter cabinet",
      "business_service": "",
      "type": "Standard",
      "close_notes": "",
      "sys_id": "1c87925347c12200e0ef563dbb9a7177",
      "number": "CHG0040005",
      "opened_at": "2016-08-10 09:16:31",
      "sys_domain": "global",
      "state": "Scheduled",
      "justification": "",
      "sys_created_by": "admin",
      "assigned_to": ""
    },
    {
      "short_description": "New version of Blackberry service",
      "reason": "",
      "close_code": "",
      "closed_at": "",
      "backout_plan": "",
      "impact": "3 - Low",
      "description": "",
      "business_service": "",
      "type": "Normal",
      "close_notes": "",
      "sys_id": "2071a5d037310200f212cc028e41f107",
      "number": "CHG0000030",
      "opened_at": "2015-08-06 12:03:20",
      "sys_domain": "global",
      "state": "New",
      "justification": "",
      "sys_created_by": "admin",
      "assigned_to": ""
    },
    {
      "short_description": "Upgrade Tomcat server to 4.0",
      "reason": "",
      "close_code": "",
      "closed_at": "",
      "backout_plan": "",
      "impact": "3 - Low",
      "description": "Please upgrade the Tomcat server version to 3.x to 4.0",
      "business_service": "",
      "type": "Emergency",
      "close_notes": "",
      "sys_id": "20de36ec73d423002728660c4cf6a7d6",
      "number": "CHG0002001",
      "opened_at": "2018-08-30 01:02:31",
      "sys_domain": "global",
      "state": "New",
      "justification": "",
      "sys_created_by": "admin",
      "assigned_to": ""
    },
    {
      "short_description": "Deploy new Cisco Catalyst 4500",
      "reason": "",
      "close_code": "",
      "closed_at": "",
      "backout_plan": "Power down switch\nReprovision existing Cisco 2900 switch\nValidate connectivity from all private networks",
      "impact": "2 - Medium",
      "description": "The existing Cisco 2900 is being decommissioned and replaced with a Cisco 4500 that supports additional services and is still supported by Cisco.",
      "business_service": "",
      "type": "Normal",
      "close_notes": "",
      "sys_id": "21cd3552db252200a6a2b31be0b8f522",
      "number": "CHG0000059",
      "opened_at": "2023-07-22 01:21:34",
      "sys_domain": "global",
      "state": "Authorize",
      "justification": "",
      "sys_created_by": "admin",
      "assigned_to": "David Loo"
    },
    {
      "short_description": "Increase db_block_buffers from 5000 to 7500",
      "reason": "",
      "close_code": "",
      "closed_at": "",
      "backout_plan": "rollback to existing db_block_buffer setting",
      "impact": "2 - Medium",
      "description": "The database size has increased and the cache hit rate is at the low end of an acceptable rate. The Database team needss to increase the amount of memory allocated to the Oracle SGA to increase the cache hit rate.",
      "business_service": "",
      "type": "Normal",
      "close_notes": "",
      "sys_id": "21cdf152db252200a6a2b31be0b8f592",
      "number": "CHG0000054",
      "opened_at": "2023-07-22 01:21:33",
      "sys_domain": "global",
      "state": "Authorize",
      "justification": "",
      "sys_created_by": "admin",
      "assigned_to": "David Loo"
    },
    {
      "short_description": "Upgrade OWA-SD-01 to MS Windows Server 2016",
      "reason": "",
      "close_code": "",
      "closed_at": "",
      "backout_plan": "re-image OWA-SD-01\nVerify network connectivity\nValidate OWA access using owa_test1 and owa_test2 test users\nFail from DR system back to OWA-SD-01",
      "impact": "2 - Medium",
      "description": "",
      "business_service": "",
      "type": "Normal",
      "close_notes": "",
      "sys_id": "25cdf152db252200a6a2b31be0b8f5ca",
      "number": "CHG0000055",
      "opened_at": "2023-07-22 01:21:33",
      "sys_domain": "global",
      "state": "Authorize",
      "justification": "",
      "sys_created_by": "admin",
      "assigned_to": "David Loo"
    },
    {
      "short_description": "Roger Dec 5 v2",
      "reason": "",
      "close_code": "",
      "closed_at": "",
      "backout_plan": "",
      "impact": "3 - Low",
      "description": "ASDF.....",
      "business_service": "",
      "type": "Emergency",
      "close_notes": "",
      "sys_id": "27ada47b97323110de1dfa67f053af4e",
      "number": "CHG0030023",
      "opened_at": "2023-12-05 12:05:59",
      "sys_domain": "global",
      "state": "New",
      "justification": "",
      "sys_created_by": "abel.tuter",
      "assigned_to": ""
    },
    {
      "short_description": "Update default support group on all Oracle CI's to Database group",
      "reason": "",
      "close_code": "",
      "closed_at": "",
      "backout_plan": "",
      "impact": "3 - Low",
      "description": "The default support group for all Oracle CI's is being transitioned to the Database group",
      "business_service": "",
      "type": "Normal",
      "close_notes": "",
      "sys_id": "29cd3552db252200a6a2b31be0b8f528",
      "number": "CHG0000060",
      "opened_at": "2023-07-22 01:21:34",
      "sys_domain": "global",
      "state": "Authorize",
      "justification": "Database group taking over all \nOracle database support activities",
      "sys_created_by": "admin",
      "assigned_to": "Bow Ruggeri"
    },
    {
      "short_description": "Update /etc/network/interfaces to include name servers 8.8.8.8 & 8.8.4.4",
      "reason": "",
      "close_code": "",
      "closed_at": "",
      "backout_plan": "Comment out new line in /etc/network/interfaces",
      "impact": "2 - Medium",
      "description": "We need to add additional redundant name servers to lnux100, lnux101 and PS LinuxApp01",
      "business_service": "",
      "type": "Normal",
      "close_notes": "",
      "sys_id": "29cdf152db252200a6a2b31be0b8f58b",
      "number": "CHG0000053",
      "opened_at": "2023-07-22 01:21:33",
      "sys_domain": "global",
      "state": "Authorize",
      "justification": "",
      "sys_created_by": "admin",
      "assigned_to": "Bow Ruggeri"
    },
    {
      "short_description": "Change default router on unix201",
      "reason": "",
      "close_code": "",
      "closed_at": "",
      "backout_plan": "revert to default gateway 192.168.1.100\nRestart network with /etc/init.d/network restart\ntest network connectivity using ping 192.168.1.254\ntest network connectivity using ping 10.10.100.10",
      "impact": "3 - Low",
      "description": "",
      "business_service": "",
      "type": "Normal",
      "close_notes": "",
      "sys_id": "2dcdf152db252200a6a2b31be0b8f5d0",
      "number": "CHG0000056",
      "opened_at": "2023-07-22 01:21:33",
      "sys_domain": "global",
      "state": "Authorize",
      "justification": "",
      "sys_created_by": "admin",
      "assigned_to": "David Loo"
    },
    {
      "short_description": "Add network switch to cabinet",
      "reason": "",
      "close_code": "",
      "closed_at": "",
      "backout_plan": "-- Physically remove switch and all associated cabling\n-- Remove switch from management, monitoring and ServiceNow CMDB",
      "impact": "3 - Low",
      "description": "This standard change template describes adding a new network switch to a datacenter cabinet",
      "business_service": "",
      "type": "Standard",
      "close_notes": "",
      "sys_id": "2de5121347c12200e0ef563dbb9a71eb",
      "number": "CHG0040001",
      "opened_at": "2016-08-10 09:09:29",
      "sys_domain": "global",
      "state": "New",
      "justification": "",
      "sys_created_by": "admin",
      "assigned_to": ""
    },
    {
      "short_description": "Update ownership of Blackberry service",
      "reason": "",
      "close_code": "",
      "closed_at": "",
      "backout_plan": "",
      "impact": "3 - Low",
      "description": "",
      "business_service": "",
      "type": "Normal",
      "close_notes": "",
      "sys_id": "30c1e5d037310200f212cc028e41f158",
      "number": "CHG0000031",
      "opened_at": "2015-08-06 12:04:43",
      "sys_domain": "global",
      "state": "New",
      "justification": "",
      "sys_created_by": "admin",
      "assigned_to": ""
    },
    {
      "short_description": "Update /etc/network/interfaces to include name servers 8.8.8.8 & 8.8.4.4",
      "reason": "",
      "close_code": "",
      "closed_at": "",
      "backout_plan": "Comment out new line in /etc/network/interfaces",
      "impact": "2 - Medium",
      "description": "We need to add additional redundant name servers to lnux100, lnux101 and PS LinuxApp01",
      "business_service": "",
      "type": "Normal",
      "close_notes": "",
      "sys_id": "31cd7552db252200a6a2b31be0b8f55c",
      "number": "CHG0000071",
      "opened_at": "2023-07-22 01:21:35",
      "sys_domain": "global",
      "state": "Authorize",
      "justification": "",
      "sys_created_by": "admin",
      "assigned_to": "Bow Ruggeri"
    },
    {
      "short_description": "Upgrade OWA-SD-01 to MS Windows Server 2016",
      "reason": "",
      "close_code": "",
      "closed_at": "",
      "backout_plan": "re-image OWA-SD-01\nVerify network connectivity\nValidate OWA access using owa_test1 and owa_test2 test users\nFail from DR system back to OWA-SD-01",
      "impact": "2 - Medium",
      "description": "",
      "business_service": "",
      "type": "Normal",
      "close_notes": "",
      "sys_id": "35cd3552db252200a6a2b31be0b8f5de",
      "number": "CHG0000065",
      "opened_at": "2023-07-22 01:21:34",
      "sys_domain": "global",
      "state": "Authorize",
      "justification": "",
      "sys_created_by": "admin",
      "assigned_to": "David Loo"
    },
    {
      "short_description": "A failed RAID controller card needs to be replaced on PSORA1",
      "reason": "",
      "close_code": "",
      "closed_at": "",
      "backout_plan": "",
      "impact": "2 - Medium",
      "description": "01:00.0 RAID bus controller: Adaptec AAC-RAID has failed on PSORA1 and needs to be replaced immediately.",
      "business_service": "",
      "type": "Normal",
      "close_notes": "",
      "sys_id": "35cd7552db252200a6a2b31be0b8f51d",
      "number": "CHG0000067",
      "opened_at": "2023-07-22 01:21:34",
      "sys_domain": "global",
      "state": "Authorize",
      "justification": "",
      "sys_created_by": "admin",
      "assigned_to": "David Loo"
    },
    {
      "short_description": "",
      "reason": "",
      "close_code": "",
      "closed_at": "",
      "backout_plan": "",
      "impact": "3 - Low",
      "description": "",
      "business_service": "",
      "type": "Normal",
      "close_notes": "",
      "sys_id": "39b8040597513110de1dfa67f053afe9",
      "number": "CHG0030004",
      "opened_at": "2023-09-13 07:47:01",
      "sys_domain": "global",
      "state": "New",
      "justification": "",
      "sys_created_by": "admin",
      "assigned_to": ""
    },
    {
      "short_description": "Update default support group on all Oracle CI's to Database group",
      "reason": "",
      "close_code": "",
      "closed_at": "",
      "backout_plan": "",
      "impact": "3 - Low",
      "description": "The default support group for all Oracle CI's is being transitioned to the Database group",
      "business_service": "",
      "type": "Normal",
      "close_notes": "",
      "sys_id": "39cd7552db252200a6a2b31be0b8f555",
      "number": "CHG0000070",
      "opened_at": "2023-07-22 01:21:35",
      "sys_domain": "global",
      "state": "Authorize",
      "justification": "Database group taking over all \nOracle database support activities",
      "sys_created_by": "admin",
      "assigned_to": "Bow Ruggeri"
    },
    {
      "short_description": "Change default router on unix201",
      "reason": "",
      "close_code": "",
      "closed_at": "",
      "backout_plan": "revert to default gateway 192.168.1.100\nRestart network with /etc/init.d/network restart\ntest network connectivity using ping 192.168.1.254\ntest network connectivity using ping 10.10.100.10",
      "impact": "3 - Low",
      "description": "",
      "business_service": "",
      "type": "Normal",
      "close_notes": "",
      "sys_id": "3dcd3552db252200a6a2b31be0b8f5e4",
      "number": "CHG0000066",
      "opened_at": "2023-07-22 01:21:34",
      "sys_domain": "global",
      "state": "Authorize",
      "justification": "",
      "sys_created_by": "admin",
      "assigned_to": "David Loo"
    },
    {
      "short_description": "A failed RAID controller card needs to be replaced on PSORA1",
      "reason": "",
      "close_code": "",
      "closed_at": "",
      "backout_plan": "",
      "impact": "2 - Medium",
      "description": "01:00.0 RAID bus controller: Adaptec AAC-RAID has failed on PSORA1 and needs to be replaced immediately.",
      "business_service": "",
      "type": "Normal",
      "close_notes": "",
      "sys_id": "41cdb152db252200a6a2b31be0b8f527",
      "number": "CHG0000037",
      "opened_at": "2023-07-22 01:21:31",
      "sys_domain": "global",
      "state": "Authorize",
      "justification": "",
      "sys_created_by": "admin",
      "assigned_to": "David Loo"
    },
    {
      "short_description": "Install new Cisco",
      "reason": "",
      "close_code": "",
      "closed_at": "",
      "backout_plan": "",
      "impact": "3 - Low",
      "description": "Please install new Cat. 6500 in Data center 01\n        ",
      "business_service": "",
      "type": "Normal",
      "close_notes": "",
      "sys_id": "46cb2f54a9fe198101cf6814a2754606",
      "number": "CHG0000008",
      "opened_at": "2022-11-10 15:14:14",
      "sys_domain": "global",
      "state": "Assess",
      "justification": "",
      "sys_created_by": "glide.maint",
      "assigned_to": "ITIL User"
    },
    {
      "short_description": "Install new PBX",
      "reason": "",
      "close_code": "",
      "closed_at": "2023-07-20 02:46:07",
      "backout_plan": "",
      "impact": "3 - Low",
      "description": "",
      "business_service": "",
      "type": "Normal",
      "close_notes": "",
      "sys_id": "46cc713aa9fe1981008a95d213681c65",
      "number": "CHG0000005",
      "opened_at": "2022-11-10 15:15:36",
      "sys_domain": "global",
      "state": "Implement",
      "justification": "",
      "sys_created_by": "glide.maint",
      "assigned_to": "David Loo"
    },
    {
      "short_description": "Upgrade NY RAC to Oracle 12c",
      "reason": "",
      "close_code": "",
      "closed_at": "",
      "backout_plan": "Restore Oracle 11g binaries\nRestore Oracle 11g data files\nEnable Oracle Listener\nTest connectivity from PS LinuxApp01\nTest connectivity from PS LinuxApp02",
      "impact": "3 - Low",
      "description": "NY RAC instance needs to be upgraded from Oracle 11g to Oracle 12c",
      "business_service": "",
      "type": "Normal",
      "close_notes": "",
      "sys_id": "49cdb152db252200a6a2b31be0b8f548",
      "number": "CHG0000038",
      "opened_at": "2023-07-22 01:21:31",
      "sys_domain": "global",
      "state": "Authorize",
      "justification": "",
      "sys_created_by": "admin",
      "assigned_to": "Fred Luddy"
    },
    {
      "short_description": "Update /etc/network/interfaces to include name servers 8.8.8.8 & 8.8.4.4",
      "reason": "",
      "close_code": "",
      "closed_at": "",
      "backout_plan": "Comment out new line in /etc/network/interfaces",
      "impact": "2 - Medium",
      "description": "We need to add additional redundant name servers to lnux100, lnux101 and PS LinuxApp01",
      "business_service": "",
      "type": "Normal",
      "close_notes": "",
      "sys_id": "49cdb152db252200a6a2b31be0b8f569",
      "number": "CHG0000041",
      "opened_at": "2023-07-22 01:21:32",
      "sys_domain": "global",
      "state": "Authorize",
      "justification": "",
      "sys_created_by": "admin",
      "assigned_to": "Bow Ruggeri"
    },
    {
      "short_description": "asdf",
      "reason": "",
      "close_code": "",
      "closed_at": "",
      "backout_plan": "",
      "impact": "3 - Low",
      "description": "",
      "business_service": "",
      "type": "Emergency",
      "close_notes": "",
      "sys_id": "4f0ff93097523110de1dfa67f053af38",
      "number": "CHG0030013",
      "opened_at": "2023-11-01 14:48:19",
      "sys_domain": "global",
      "state": "New",
      "justification": "",
      "sys_created_by": "abel.tuter",
      "assigned_to": ""
    },
    {
      "short_description": "",
      "reason": "",
      "close_code": "",
      "closed_at": "",
      "backout_plan": "",
      "impact": "3 - Low",
      "description": "",
      "business_service": "",
      "type": "Normal",
      "close_notes": "",
      "sys_id": "4f58084197513110de1dfa67f053afe7",
      "number": "CHG0030003",
      "opened_at": "2023-09-13 07:45:28",
      "sys_domain": "global",
      "state": "New",
      "justification": "",
      "sys_created_by": "admin",
      "assigned_to": ""
    },
    {
      "short_description": "Change default router on unix201",
      "reason": "",
      "close_code": "",
      "closed_at": "",
      "backout_plan": "revert to default gateway 192.168.1.100\nRestart network with /etc/init.d/network restart\ntest network connectivity using ping 192.168.1.254\ntest network connectivity using ping 10.10.100.10",
      "impact": "3 - Low",
      "description": "",
      "business_service": "",
      "type": "Normal",
      "close_notes": "",
      "sys_id": "55cdb152db252200a6a2b31be0b8f5ee",
      "number": "CHG0000046",
      "opened_at": "2023-07-22 01:21:32",
      "sys_domain": "global",
      "state": "Authorize",
      "justification": "",
      "sys_created_by": "admin",
      "assigned_to": "David Loo"
    },
    {
      "short_description": "Update /etc/network/interfaces to include name servers 8.8.8.8 & 8.8.4.4",
      "reason": "",
      "close_code": "",
      "closed_at": "",
      "backout_plan": "Comment out new line in /etc/network/interfaces",
      "impact": "2 - Medium",
      "description": "We need to add additional redundant name servers to lnux100, lnux101 and PS LinuxApp01",
      "business_service": "",
      "type": "Normal",
      "close_notes": "",
      "sys_id": "55cdf152db252200a6a2b31be0b8f540",
      "number": "CHG0000051",
      "opened_at": "2023-07-22 01:21:33",
      "sys_domain": "global",
      "state": "Authorize",
      "justification": "",
      "sys_created_by": "admin",
      "assigned_to": "Bow Ruggeri"
    },
    {
      "short_description": "A failed RAID controller card needs to be replaced on PSORA1",
      "reason": "",
      "close_code": "",
      "closed_at": "",
      "backout_plan": "",
      "impact": "2 - Medium",
      "description": "01:00.0 RAID bus controller: Adaptec AAC-RAID has failed on PSORA1 and needs to be replaced immediately.",
      "business_service": "",
      "type": "Normal",
      "close_notes": "",
      "sys_id": "5acdb552db252200a6a2b31be0b8f5bc",
      "number": "CHG0000087",
      "opened_at": "2023-07-22 01:21:36",
      "sys_domain": "global",
      "state": "Authorize",
      "justification": "",
      "sys_created_by": "admin",
      "assigned_to": "David Loo"
    },
    {
      "short_description": "Update /etc/network/interfaces to include name servers 8.8.8.8 & 8.8.4.4",
      "reason": "",
      "close_code": "",
      "closed_at": "",
      "backout_plan": "Comment out new line in /etc/network/interfaces",
      "impact": "2 - Medium",
      "description": "We need to add additional redundant name servers to lnux100, lnux101 and PS LinuxApp01",
      "business_service": "",
      "type": "Normal",
      "close_notes": "",
      "sys_id": "5dcdf152db252200a6a2b31be0b8f546",
      "number": "CHG0000052",
      "opened_at": "2023-07-22 01:21:33",
      "sys_domain": "global",
      "state": "Authorize",
      "justification": "",
      "sys_created_by": "admin",
      "assigned_to": "Bow Ruggeri"
    },
    {
      "short_description": "Change default router on unix201",
      "reason": "",
      "close_code": "",
      "closed_at": "",
      "backout_plan": "revert to default gateway 192.168.1.100\nRestart network with /etc/init.d/network restart\ntest network connectivity using ping 192.168.1.254\ntest network connectivity using ping 10.10.100.10",
      "impact": "3 - Low",
      "description": "",
      "business_service": "",
      "type": "Normal",
      "close_notes": "",
      "sys_id": "5ecdb552db252200a6a2b31be0b8f5b5",
      "number": "CHG0000086",
      "opened_at": "2023-07-22 01:21:36",
      "sys_domain": "global",
      "state": "Authorize",
      "justification": "",
      "sys_created_by": "admin",
      "assigned_to": "David Loo"
    },
    {
      "short_description": "Increase db_block_buffers from 5000 to 7500",
      "reason": "",
      "close_code": "",
      "closed_at": "",
      "backout_plan": "rollback to existing db_block_buffer setting",
      "impact": "2 - Medium",
      "description": "The database size has increased and the cache hit rate is at the low end of an acceptable rate. The Database team needss to increase the amount of memory allocated to the Oracle SGA to increase the cache hit rate.",
      "business_service": "",
      "type": "Normal",
      "close_notes": "",
      "sys_id": "66cdf552db252200a6a2b31be0b8f559",
      "number": "CHG0000094",
      "opened_at": "2023-07-22 01:21:37",
      "sys_domain": "global",
      "state": "Authorize",
      "justification": "",
      "sys_created_by": "admin",
      "assigned_to": "David Loo"
    },
    {
      "short_description": "A failed RAID controller card needs to be replaced on PSORA1",
      "reason": "",
      "close_code": "",
      "closed_at": "",
      "backout_plan": "",
      "impact": "2 - Medium",
      "description": "01:00.0 RAID bus controller: Adaptec AAC-RAID has failed on PSORA1 and needs to be replaced immediately.",
      "business_service": "",
      "type": "Normal",
      "close_notes": "",
      "sys_id": "6dcdf152db252200a6a2b31be0b8f5fc",
      "number": "CHG0000057",
      "opened_at": "2023-07-22 01:21:33",
      "sys_domain": "global",
      "state": "Authorize",
      "justification": "",
      "sys_created_by": "admin",
      "assigned_to": "David Loo"
    },
    {
      "short_description": "Change request for server",
      "reason": "",
      "close_code": "",
      "closed_at": "",
      "backout_plan": "",
      "impact": "3 - Low",
      "description": "NOthing....",
      "business_service": "",
      "type": "Normal",
      "close_notes": "",
      "sys_id": "7073132597d97110de1dfa67f053af9e",
      "number": "CHG0030009",
      "opened_at": "2023-09-15 11:49:44",
      "sys_domain": "global",
      "state": "New",
      "justification": "",
      "sys_created_by": "abel.tuter",
      "assigned_to": ""
    },
    {
      "short_description": "",
      "reason": "",
      "close_code": "",
      "closed_at": "",
      "backout_plan": "",
      "impact": "3 - Low",
      "description": "",
      "business_service": "",
      "type": "Normal",
      "close_notes": "",
      "sys_id": "7148cc8197513110de1dfa67f053afe0",
      "number": "CHG0030002",
      "opened_at": "2023-09-13 07:45:06",
      "sys_domain": "global",
      "state": "New",
      "justification": "",
      "sys_created_by": "admin",
      "assigned_to": ""
    },
    {
      "short_description": "Nov 9",
      "reason": "",
      "close_code": "Unsuccessful",
      "closed_at": "",
      "backout_plan": "",
      "impact": "3 - Low",
      "description": "",
      "business_service": "",
      "type": "Emergency",
      "close_notes": "Didn't work",
      "sys_id": "7cce5f1f975e7110de1dfa67f053afe5",
      "number": "CHG0030014",
      "opened_at": "2023-11-09 15:11:19",
      "sys_domain": "global",
      "state": "New",
      "justification": "",
      "sys_created_by": "admin",
      "assigned_to": ""
    },
    {
      "short_description": "Update /etc/network/interfaces to include name servers 8.8.8.8 & 8.8.4.4",
      "reason": "",
      "close_code": "",
      "closed_at": "",
      "backout_plan": "Comment out new line in /etc/network/interfaces",
      "impact": "2 - Medium",
      "description": "We need to add additional redundant name servers to lnux100, lnux101 and PS LinuxApp01",
      "business_service": "",
      "type": "Normal",
      "close_notes": "",
      "sys_id": "81cdb152db252200a6a2b31be0b8f589",
      "number": "CHG0000042",
      "opened_at": "2023-07-22 01:21:32",
      "sys_domain": "global",
      "state": "Authorize",
      "justification": "",
      "sys_created_by": "admin",
      "assigned_to": "Bow Ruggeri"
    },
    {
      "short_description": "Java Application Server change",
      "reason": "",
      "close_code": "",
      "closed_at": "",
      "backout_plan": "",
      "impact": "3 - Low",
      "description": "",
      "business_service": "",
      "type": "Normal",
      "close_notes": "",
      "sys_id": "8799385b0a0a2c3e14c041a7f5414266",
      "number": "CHG0000010",
      "opened_at": "2024-06-03 02:52:34",
      "sys_domain": "global",
      "state": "New",
      "justification": "",
      "sys_created_by": "felix.bait",
      "assigned_to": "Don Goodliffe"
    },
    {
      "short_description": "Another Java Application Server change\n        ",
      "reason": "",
      "close_code": "",
      "closed_at": "",
      "backout_plan": "",
      "impact": "3 - Low",
      "description": "",
      "business_service": "",
      "type": "Normal",
      "close_notes": "",
      "sys_id": "87a143900a0a2c3e386e50e022df4c99",
      "number": "CHG0000011",
      "opened_at": "2024-12-16 02:01:21",
      "sys_domain": "global",
      "state": "New",
      "justification": "",
      "sys_created_by": "felix.bait",
      "assigned_to": "David Loo"
    },
    {
      "short_description": "Java App Server",
      "reason": "",
      "close_code": "",
      "closed_at": "",
      "backout_plan": "",
      "impact": "3 - Low",
      "description": "",
      "business_service": "",
      "type": "Normal",
      "close_notes": "",
      "sys_id": "87a4037a0a0a2c3e4f9c822ac29cb2ed",
      "number": "CHG0000012",
      "opened_at": "2024-12-16 02:04:21",
      "sys_domain": "global",
      "state": "New",
      "justification": "",
      "sys_created_by": "felix.bait",
      "assigned_to": "Charlie Whitherspoon"
    },
    {
      "short_description": "Oracle FLX (Java App Dependency)\n        ",
      "reason": "",
      "close_code": "",
      "closed_at": "",
      "backout_plan": "",
      "impact": "3 - Low",
      "description": "",
      "business_service": "",
      "type": "Normal",
      "close_notes": "",
      "sys_id": "87ae5e900a0a2c3e263e8304e727c646",
      "number": "CHG0000013",
      "opened_at": "2024-12-16 02:15:40",
      "sys_domain": "global",
      "state": "New",
      "justification": "",
      "sys_created_by": "felix.bait",
      "assigned_to": "Fred Luddy"
    },
    {
      "short_description": "CMS App FLX (depends on Java Apps FLX)\n        ",
      "reason": "",
      "close_code": "",
      "closed_at": "",
      "backout_plan": "",
      "impact": "3 - Low",
      "description": "",
      "business_service": "",
      "type": "Normal",
      "close_notes": "",
      "sys_id": "87b1682a0a0a2c3e75af785bd9073d70",
      "number": "CHG0000014",
      "opened_at": "2024-12-16 02:18:59",
      "sys_domain": "global",
      "state": "New",
      "justification": "",
      "sys_created_by": "felix.bait",
      "assigned_to": "Christen Mitchell"
    },
    {
      "short_description": "Unix update",
      "reason": "",
      "close_code": "",
      "closed_at": "",
      "backout_plan": "",
      "impact": "3 - Low",
      "description": "",
      "business_service": "",
      "type": "Normal",
      "close_notes": "",
      "sys_id": "8857dba437501000bff8e0f6177334fc",
      "number": "CHG0000015",
      "opened_at": "2024-02-05 03:25:04",
      "sys_domain": "global",
      "state": "New",
      "justification": "",
      "sys_created_by": "felix.bait",
      "assigned_to": "Bud Richman"
    },
    {
      "short_description": "Update default support group on all Oracle CI's to Database group",
      "reason": "",
      "close_code": "",
      "closed_at": "",
      "backout_plan": "",
      "impact": "3 - Low",
      "description": "The default support group for all Oracle CI's is being transitioned to the Database group",
      "business_service": "",
      "type": "Normal",
      "close_notes": "",
      "sys_id": "8dcdb152db252200a6a2b31be0b8f562",
      "number": "CHG0000040",
      "opened_at": "2023-07-22 01:21:31",
      "sys_domain": "global",
      "state": "Authorize",
      "justification": "Database group taking over all \nOracle database support activities",
      "sys_created_by": "admin",
      "assigned_to": "Bow Ruggeri"
    },
    {
      "short_description": "Update /etc/network/interfaces to include name servers 8.8.8.8 & 8.8.4.4",
      "reason": "",
      "close_code": "",
      "closed_at": "",
      "backout_plan": "Comment out new line in /etc/network/interfaces",
      "impact": "2 - Medium",
      "description": "We need to add additional redundant name servers to lnux100, lnux101 and PS LinuxApp01",
      "business_service": "",
      "type": "Normal",
      "close_notes": "",
      "sys_id": "8ecd7552db252200a6a2b31be0b8f581",
      "number": "CHG0000073",
      "opened_at": "2023-07-22 01:21:35",
      "sys_domain": "global",
      "state": "Authorize",
      "justification": "",
      "sys_created_by": "admin",
      "assigned_to": "Bow Ruggeri"
    },
    {
      "short_description": "A failed RAID controller card needs to be replaced on PSORA1",
      "reason": "",
      "close_code": "",
      "closed_at": "",
      "backout_plan": "",
      "impact": "2 - Medium",
      "description": "01:00.0 RAID bus controller: Adaptec AAC-RAID has failed on PSORA1 and needs to be replaced immediately.",
      "business_service": "",
      "type": "Normal",
      "close_notes": "",
      "sys_id": "91cdf152db252200a6a2b31be0b8f50e",
      "number": "CHG0000047",
      "opened_at": "2023-07-22 01:21:32",
      "sys_domain": "global",
      "state": "Authorize",
      "justification": "",
      "sys_created_by": "admin",
      "assigned_to": "David Loo"
    },
    {
      "short_description": "Update /etc/network/interfaces to include name servers 8.8.8.8 & 8.8.4.4",
      "reason": "",
      "close_code": "",
      "closed_at": "",
      "backout_plan": "Comment out new line in /etc/network/interfaces",
      "impact": "2 - Medium",
      "description": "We need to add additional redundant name servers to lnux100, lnux101 and PS LinuxApp01",
      "business_service": "",
      "type": "Normal",
      "close_notes": "",
      "sys_id": "92cdb552db252200a6a2b31be0b8f564",
      "number": "CHG0000083",
      "opened_at": "2023-07-22 01:21:36",
      "sys_domain": "global",
      "state": "Authorize",
      "justification": "",
      "sys_created_by": "admin",
      "assigned_to": "Bow Ruggeri"
    },
    {
      "short_description": "Update default support group on all Oracle CI's to Database group",
      "reason": "",
      "close_code": "",
      "closed_at": "",
      "backout_plan": "",
      "impact": "3 - Low",
      "description": "The default support group for all Oracle CI's is being transitioned to the Database group",
      "business_service": "",
      "type": "Normal",
      "close_notes": "",
      "sys_id": "92cdf552db252200a6a2b31be0b8f501",
      "number": "CHG0000090",
      "opened_at": "2023-07-22 01:21:37",
      "sys_domain": "global",
      "state": "Authorize",
      "justification": "Database group taking over all \nOracle database support activities",
      "sys_created_by": "admin",
      "assigned_to": "Bow Ruggeri"
    },
    {
      "short_description": "",
      "reason": "",
      "close_code": "",
      "closed_at": "",
      "backout_plan": "",
      "impact": "3 - Low",
      "description": "teaintDec5",
      "business_service": "",
      "type": "Normal",
      "close_notes": "",
      "sys_id": "93dc20bb97323110de1dfa67f053af4f",
      "number": "CHG0030022",
      "opened_at": "2023-12-05 12:02:25",
      "sys_domain": "global",
      "state": "New",
      "justification": "",
      "sys_created_by": "abel.tuter",
      "assigned_to": ""
    },
    {
      "short_description": "Update default support group on all Oracle CI's to Database group",
      "reason": "",
      "close_code": "",
      "closed_at": "",
      "backout_plan": "",
      "impact": "3 - Low",
      "description": "The default support group for all Oracle CI's is being transitioned to the Database group",
      "business_service": "",
      "type": "Normal",
      "close_notes": "",
      "sys_id": "95cdf152db252200a6a2b31be0b8f52d",
      "number": "CHG0000050",
      "opened_at": "2023-07-22 01:21:33",
      "sys_domain": "global",
      "state": "Authorize",
      "justification": "Database group taking over all \nOracle database support activities",
      "sys_created_by": "admin",
      "assigned_to": "Bow Ruggeri"
    },
    {
      "short_description": "Testing Kenny",
      "reason": "",
      "close_code": "",
      "closed_at": "",
      "backout_plan": "",
      "impact": "3 - Low",
      "description": "",
      "business_service": "",
      "type": "Normal",
      "close_notes": "",
      "sys_id": "986be47b97323110de1dfa67f053af52",
      "number": "CHG0030021",
      "opened_at": "2023-12-05 11:55:56",
      "sys_domain": "global",
      "state": "New",
      "justification": "",
      "sys_created_by": "abel.tuter",
      "assigned_to": ""
    },
    {
      "short_description": "Upgrade OWA-SD-01 to MS Windows Server 2016",
      "reason": "",
      "close_code": "",
      "closed_at": "",
      "backout_plan": "re-image OWA-SD-01\nVerify network connectivity\nValidate OWA access using owa_test1 and owa_test2 test users\nFail from DR system back to OWA-SD-01",
      "impact": "2 - Medium",
      "description": "",
      "business_service": "",
      "type": "Normal",
      "close_notes": "",
      "sys_id": "99cdb152db252200a6a2b31be0b8f5e7",
      "number": "CHG0000045",
      "opened_at": "2023-07-22 01:21:32",
      "sys_domain": "global",
      "state": "Authorize",
      "justification": "",
      "sys_created_by": "admin",
      "assigned_to": "David Loo"
    },
    {
      "short_description": "Oct 19",
      "reason": "",
      "close_code": "",
      "closed_at": "",
      "backout_plan": "",
      "impact": "3 - Low",
      "description": "",
      "business_service": "",
      "type": "Emergency",
      "close_notes": "",
      "sys_id": "9acab6e497863110de1dfa67f053afcc",
      "number": "CHG0030010",
      "opened_at": "2023-10-19 14:15:08",
      "sys_domain": "global",
      "state": "New",
      "justification": "",
      "sys_created_by": "abel.tuter",
      "assigned_to": ""
    },
    {
      "short_description": "Update /etc/network/interfaces to include name servers 8.8.8.8 & 8.8.4.4",
      "reason": "",
      "close_code": "",
      "closed_at": "",
      "backout_plan": "Comment out new line in /etc/network/interfaces",
      "impact": "2 - Medium",
      "description": "We need to add additional redundant name servers to lnux100, lnux101 and PS LinuxApp01",
      "business_service": "",
      "type": "Normal",
      "close_notes": "",
      "sys_id": "9acdb552db252200a6a2b31be0b8f55d",
      "number": "CHG0000082",
      "opened_at": "2023-07-22 01:21:36",
      "sys_domain": "global",
      "state": "Authorize",
      "justification": "",
      "sys_created_by": "admin",
      "assigned_to": "Bow Ruggeri"
    },
    {
      "short_description": "Update /etc/network/interfaces to include name servers 8.8.8.8 & 8.8.4.4",
      "reason": "",
      "close_code": "",
      "closed_at": "",
      "backout_plan": "Comment out new line in /etc/network/interfaces",
      "impact": "2 - Medium",
      "description": "We need to add additional redundant name servers to lnux100, lnux101 and PS LinuxApp01",
      "business_service": "",
      "type": "Normal",
      "close_notes": "",
      "sys_id": "9acdf552db252200a6a2b31be0b8f507",
      "number": "CHG0000091",
      "opened_at": "2023-07-22 01:21:37",
      "sys_domain": "global",
      "state": "Authorize",
      "justification": "",
      "sys_created_by": "admin",
      "assigned_to": "Bow Ruggeri"
    },
    {
      "short_description": "Put another 100 Gb drive on the 2nd Floor Server\n        ",
      "reason": "",
      "close_code": "",
      "closed_at": "2023-07-20 02:46:02",
      "backout_plan": "",
      "impact": "3 - Low",
      "description": "We're going to put another 100 GB drive on the floor 2\n            server.\n\n            Needs a 100 GB SCSI II Ultra Drive.\n        ",
      "business_service": "",
      "type": "Normal",
      "close_notes": "",
      "sys_id": "9d3f823bc611228700376cc3b4b5b87b",
      "number": "CHG0000006",
      "opened_at": "2021-05-29 15:37:58",
      "sys_domain": "global",
      "state": "Scheduled",
      "justification": "",
      "sys_created_by": "pat",
      "assigned_to": "ITIL User"
    },
    {
      "short_description": "R&D wants to know what it'd cost to switch them\n            over to Linux desktops\n        ",
      "reason": "",
      "close_code": "",
      "closed_at": "2023-07-20 02:45:55",
      "backout_plan": "",
      "impact": "3 - Low",
      "description": "The new VP of R&D is thinking of switching the\n            engineers over to Linux desktops and wants to know what it'd take on\n            our end to support them, what it would cost to install them, and how\n            fast the whole thing could happen.\n        ",
      "business_service": "",
      "type": "Normal",
      "close_notes": "",
      "sys_id": "9d457fbac6112287007379b57c6b2e60",
      "number": "CHG0000007",
      "opened_at": "2021-05-29 15:44:30",
      "sys_domain": "global",
      "state": "Authorize",
      "justification": "",
      "sys_created_by": "pat",
      "assigned_to": "ITIL User"
    },
    {
      "short_description": "Deploy new Cisco Catalyst 4500",
      "reason": "",
      "close_code": "",
      "closed_at": "",
      "backout_plan": "Power down switch\nReprovision existing Cisco 2900 switch\nValidate connectivity from all private networks",
      "impact": "2 - Medium",
      "description": "The existing Cisco 2900 is being decommissioned and replaced with a Cisco 4500 that supports additional services and is still supported by Cisco.",
      "business_service": "",
      "type": "Normal",
      "close_notes": "",
      "sys_id": "9dcdf152db252200a6a2b31be0b8f526",
      "number": "CHG0000049",
      "opened_at": "2023-07-22 01:21:32",
      "sys_domain": "global",
      "state": "Authorize",
      "justification": "",
      "sys_created_by": "admin",
      "assigned_to": "David Loo"
    },
    {
      "short_description": "Update location of Blackberry service",
      "reason": "",
      "close_code": "",
      "closed_at": "",
      "backout_plan": "",
      "impact": "3 - Low",
      "description": "",
      "business_service": "",
      "type": "Normal",
      "close_notes": "",
      "sys_id": "a0701a1037310200f212cc028e41f14d",
      "number": "CHG0000032",
      "opened_at": "2015-08-06 15:28:41",
      "sys_domain": "global",
      "state": "New",
      "justification": "",
      "sys_created_by": "admin",
      "assigned_to": ""
    },
    {
      "short_description": "Upgrade database server - bond_trading_uk to Postgres SQL",
      "reason": "",
      "close_code": "",
      "closed_at": "",
      "backout_plan": "",
      "impact": "3 - Low",
      "description": "",
      "business_service": "",
      "type": "Normal",
      "close_notes": "",
      "sys_id": "a36ffb7137310200f212cc028e41f13d",
      "number": "CHG0000033",
      "opened_at": "2015-08-11 15:24:29",
      "sys_domain": "global",
      "state": "New",
      "justification": "",
      "sys_created_by": "admin",
      "assigned_to": ""
    },
    {
      "short_description": "Upgrade NY RAC to Oracle 12c",
      "reason": "",
      "close_code": "",
      "closed_at": "",
      "backout_plan": "Restore Oracle 11g binaries\nRestore Oracle 11g data files\nEnable Oracle Listener\nTest connectivity from PS LinuxApp01\nTest connectivity from PS LinuxApp02",
      "impact": "3 - Low",
      "description": "NY RAC instance needs to be upgraded from Oracle 11g to Oracle 12c",
      "business_service": "",
      "type": "Normal",
      "close_notes": "",
      "sys_id": "a9cd3552db252200a6a2b31be0b8f502",
      "number": "CHG0000058",
      "opened_at": "2023-07-22 01:21:33",
      "sys_domain": "global",
      "state": "Authorize",
      "justification": "",
      "sys_created_by": "admin",
      "assigned_to": "Fred Luddy"
    },
    {
      "short_description": "Update /etc/network/interfaces to include name servers 8.8.8.8 & 8.8.4.4",
      "reason": "",
      "close_code": "",
      "closed_at": "",
      "backout_plan": "Comment out new line in /etc/network/interfaces",
      "impact": "2 - Medium",
      "description": "We need to add additional redundant name servers to lnux100, lnux101 and PS LinuxApp01",
      "business_service": "",
      "type": "Normal",
      "close_notes": "",
      "sys_id": "a9cd3552db252200a6a2b31be0b8f579",
      "number": "CHG0000061",
      "opened_at": "2023-07-22 01:21:34",
      "sys_domain": "global",
      "state": "Authorize",
      "justification": "",
      "sys_created_by": "admin",
      "assigned_to": "Bow Ruggeri"
    },
    {
      "short_description": "Rollback Oracle Version",
      "reason": "",
      "close_code": "",
      "closed_at": "2023-07-20 02:46:25",
      "backout_plan": "Current prod environment to be snapshotted with VmWare\n            prior to change.\n        ",
      "impact": "3 - Low",
      "description": "Performance of the Siebel SFA software has been severely\n            degraded since the upgrade performed this weekend.\n\n            We moved to an unsupported Oracle DB version. Need to rollback the\n            Oracle Instance to a supported version.\n        ",
      "business_service": "",
      "type": "Normal",
      "close_notes": "",
      "sys_id": "a9e9c33dc61122760072455df62663d2",
      "number": "CHG0000001",
      "opened_at": "2023-01-18 14:12:50",
      "sys_domain": "global",
      "state": "New",
      "justification": "",
      "sys_created_by": "admin",
      "assigned_to": "ITIL User"
    },
    {
      "short_description": "",
      "reason": "",
      "close_code": "",
      "closed_at": "",
      "backout_plan": "",
      "impact": "3 - Low",
      "description": "",
      "business_service": "",
      "type": "Normal",
      "close_notes": "",
      "sys_id": "ac09004597513110de1dfa67f053af4c",
      "number": "CHG0030005",
      "opened_at": "2023-09-13 07:48:18",
      "sys_domain": "global",
      "state": "New",
      "justification": "",
      "sys_created_by": "admin",
      "assigned_to": ""
    },
    {
      "short_description": "Add network switch to cabinet",
      "reason": "",
      "close_code": "",
      "closed_at": "",
      "backout_plan": "-- Physically remove switch and all associated cabling\n-- Remove switch from management, monitoring and ServiceNow CMDB",
      "impact": "3 - Low",
      "description": "This standard change template describes adding a new network switch to a datacenter cabinet",
      "business_service": "",
      "type": "Standard",
      "close_notes": "",
      "sys_id": "b0dbda5347c12200e0ef563dbb9a718f",
      "number": "CHG0040006",
      "opened_at": "2016-08-10 09:35:23",
      "sys_domain": "global",
      "state": "Scheduled",
      "justification": "",
      "sys_created_by": "admin",
      "assigned_to": ""
    },
    {
      "short_description": "Update /etc/network/interfaces to include name servers 8.8.8.8 & 8.8.4.4",
      "reason": "",
      "close_code": "",
      "closed_at": "",
      "backout_plan": "Comment out new line in /etc/network/interfaces",
      "impact": "2 - Medium",
      "description": "We need to add additional redundant name servers to lnux100, lnux101 and PS LinuxApp01",
      "business_service": "",
      "type": "Normal",
      "close_notes": "",
      "sys_id": "b1cd3552db252200a6a2b31be0b8f580",
      "number": "CHG0000062",
      "opened_at": "2023-07-22 01:21:34",
      "sys_domain": "global",
      "state": "Authorize",
      "justification": "",
      "sys_created_by": "admin",
      "assigned_to": "Bow Ruggeri"
    },
    {
      "short_description": "Deploy new Cisco Catalyst 4500",
      "reason": "",
      "close_code": "",
      "closed_at": "",
      "backout_plan": "Power down switch\nReprovision existing Cisco 2900 switch\nValidate connectivity from all private networks",
      "impact": "2 - Medium",
      "description": "The existing Cisco 2900 is being decommissioned and replaced with a Cisco 4500 that supports additional services and is still supported by Cisco.",
      "business_service": "",
      "type": "Normal",
      "close_notes": "",
      "sys_id": "b1cd7552db252200a6a2b31be0b8f536",
      "number": "CHG0000069",
      "opened_at": "2023-07-22 01:21:35",
      "sys_domain": "global",
      "state": "Authorize",
      "justification": "",
      "sys_created_by": "admin",
      "assigned_to": "David Loo"
    },
    {
      "short_description": "Update /etc/network/interfaces to include name servers 8.8.8.8 & 8.8.4.4",
      "reason": "",
      "close_code": "",
      "closed_at": "",
      "backout_plan": "Comment out new line in /etc/network/interfaces",
      "impact": "2 - Medium",
      "description": "We need to add additional redundant name servers to lnux100, lnux101 and PS LinuxApp01",
      "business_service": "",
      "type": "Normal",
      "close_notes": "",
      "sys_id": "b5cd7552db252200a6a2b31be0b8f57b",
      "number": "CHG0000072",
      "opened_at": "2023-07-22 01:21:35",
      "sys_domain": "global",
      "state": "Authorize",
      "justification": "",
      "sys_created_by": "admin",
      "assigned_to": "Bow Ruggeri"
    },
    {
      "short_description": "Update ownership information of database server - bond_trading_uk",
      "reason": "",
      "close_code": "",
      "closed_at": "",
      "backout_plan": "",
      "impact": "3 - Low",
      "description": "",
      "business_service": "",
      "type": "Normal",
      "close_notes": "",
      "sys_id": "baa1088237310200f212cc028e41f15c",
      "number": "CHG0000035",
      "opened_at": "2015-08-11 15:34:16",
      "sys_domain": "global",
      "state": "New",
      "justification": "",
      "sys_created_by": "admin",
      "assigned_to": ""
    },
    {
      "short_description": "Oct 23 v2",
      "reason": "",
      "close_code": "",
      "closed_at": "",
      "backout_plan": "",
      "impact": "3 - Low",
      "description": "",
      "business_service": "",
      "type": "Emergency",
      "close_notes": "",
      "sys_id": "c125167997023110de1dfa67f053af67",
      "number": "CHG0030012",
      "opened_at": "2023-10-23 08:43:04",
      "sys_domain": "global",
      "state": "New",
      "justification": "",
      "sys_created_by": "abel.tuter",
      "assigned_to": ""
    },
    {
      "short_description": "",
      "reason": "",
      "close_code": "Unsuccessful",
      "closed_at": "",
      "backout_plan": "",
      "impact": "3 - Low",
      "description": "",
      "business_service": "",
      "type": "Emergency",
      "close_notes": "Really broken",
      "sys_id": "c1dedfd3979e7110de1dfa67f053af27",
      "number": "CHG0030015",
      "opened_at": "2023-11-09 15:11:37",
      "sys_domain": "global",
      "state": "New",
      "justification": "",
      "sys_created_by": "admin",
      "assigned_to": ""
    },
    {
      "short_description": "Please reboot AS400",
      "reason": "broken",
      "close_code": "",
      "closed_at": "",
      "backout_plan": "",
      "impact": "3 - Low",
      "description": "",
      "business_service": "",
      "type": "Emergency",
      "close_notes": "",
      "sys_id": "c286d61347c12200e0ef563dbb9a71df",
      "number": "CHG0040004",
      "opened_at": "2016-08-10 09:13:54",
      "sys_domain": "global",
      "state": "New",
      "justification": "",
      "sys_created_by": "admin",
      "assigned_to": ""
    },
    {
      "short_description": "Upgrade OWA-SD-01 to MS Windows Server 2016",
      "reason": "",
      "close_code": "",
      "closed_at": "",
      "backout_plan": "re-image OWA-SD-01\nVerify network connectivity\nValidate OWA access using owa_test1 and owa_test2 test users\nFail from DR system back to OWA-SD-01",
      "impact": "2 - Medium",
      "description": "",
      "business_service": "",
      "type": "Normal",
      "close_notes": "",
      "sys_id": "c2cd7552db252200a6a2b31be0b8f5b4",
      "number": "CHG0000075",
      "opened_at": "2023-07-22 01:21:35",
      "sys_domain": "global",
      "state": "Authorize",
      "justification": "",
      "sys_created_by": "admin",
      "assigned_to": "David Loo"
    },
    {
      "short_description": "Upgrade NY RAC to Oracle 12c",
      "reason": "",
      "close_code": "",
      "closed_at": "",
      "backout_plan": "Restore Oracle 11g binaries\nRestore Oracle 11g data files\nEnable Oracle Listener\nTest connectivity from PS LinuxApp01\nTest connectivity from PS LinuxApp02",
      "impact": "3 - Low",
      "description": "NY RAC instance needs to be upgraded from Oracle 11g to Oracle 12c",
      "business_service": "",
      "type": "Normal",
      "close_notes": "",
      "sys_id": "c6cdb552db252200a6a2b31be0b8f505",
      "number": "CHG0000078",
      "opened_at": "2023-07-22 01:21:36",
      "sys_domain": "global",
      "state": "Authorize",
      "justification": "",
      "sys_created_by": "admin",
      "assigned_to": "Fred Luddy"
    },
    {
      "short_description": "Please reboot ApplicationServerPeopleSoft",
      "reason": "broken",
      "close_code": "",
      "closed_at": "",
      "backout_plan": "",
      "impact": "3 - Low",
      "description": "",
      "business_service": "",
      "type": "Emergency",
      "close_notes": "",
      "sys_id": "c83c5e5347c12200e0ef563dbb9a7190",
      "number": "CHG0040007",
      "opened_at": "2016-08-10 09:37:13",
      "sys_domain": "global",
      "state": "New",
      "justification": "",
      "sys_created_by": "admin",
      "assigned_to": ""
    },
    {
      "short_description": "Increase db_block_buffers from 5000 to 7500",
      "reason": "",
      "close_code": "",
      "closed_at": "",
      "backout_plan": "rollback to existing db_block_buffer setting",
      "impact": "2 - Medium",
      "description": "The database size has increased and the cache hit rate is at the low end of an acceptable rate. The Database team needss to increase the amount of memory allocated to the Oracle SGA to increase the cache hit rate.",
      "business_service": "",
      "type": "Normal",
      "close_notes": "",
      "sys_id": "c9cdb152db252200a6a2b31be0b8f5bb",
      "number": "CHG0000044",
      "opened_at": "2023-07-22 01:21:32",
      "sys_domain": "global",
      "state": "Authorize",
      "justification": "",
      "sys_created_by": "admin",
      "assigned_to": "David Loo"
    },
    {
      "short_description": "Increase db_block_buffers from 5000 to 7500",
      "reason": "",
      "close_code": "",
      "closed_at": "",
      "backout_plan": "rollback to existing db_block_buffer setting",
      "impact": "2 - Medium",
      "description": "The database size has increased and the cache hit rate is at the low end of an acceptable rate. The Database team needss to increase the amount of memory allocated to the Oracle SGA to increase the cache hit rate.",
      "business_service": "",
      "type": "Normal",
      "close_notes": "",
      "sys_id": "cacd7552db252200a6a2b31be0b8f5ad",
      "number": "CHG0000074",
      "opened_at": "2023-07-22 01:21:35",
      "sys_domain": "global",
      "state": "Authorize",
      "justification": "",
      "sys_created_by": "admin",
      "assigned_to": "David Loo"
    },
    {
      "short_description": "Deploy new Cisco Catalyst 4500",
      "reason": "",
      "close_code": "",
      "closed_at": "",
      "backout_plan": "Power down switch\nReprovision existing Cisco 2900 switch\nValidate connectivity from all private networks",
      "impact": "2 - Medium",
      "description": "The existing Cisco 2900 is being decommissioned and replaced with a Cisco 4500 that supports additional services and is still supported by Cisco.",
      "business_service": "",
      "type": "Normal",
      "close_notes": "",
      "sys_id": "cecdb552db252200a6a2b31be0b8f50b",
      "number": "CHG0000079",
      "opened_at": "2023-07-22 01:21:36",
      "sys_domain": "global",
      "state": "Authorize",
      "justification": "",
      "sys_created_by": "admin",
      "assigned_to": "David Loo"
    },
    {
      "short_description": "Deploy new Cisco Catalyst 4500",
      "reason": "",
      "close_code": "",
      "closed_at": "",
      "backout_plan": "Power down switch\nReprovision existing Cisco 2900 switch\nValidate connectivity from all private networks",
      "impact": "2 - Medium",
      "description": "The existing Cisco 2900 is being decommissioned and replaced with a Cisco 4500 that supports additional services and is still supported by Cisco.",
      "business_service": "",
      "type": "Normal",
      "close_notes": "",
      "sys_id": "d2cdb552db252200a6a2b31be0b8f5ee",
      "number": "CHG0000089",
      "opened_at": "2023-07-22 01:21:37",
      "sys_domain": "global",
      "state": "Authorize",
      "justification": "",
      "sys_created_by": "admin",
      "assigned_to": "David Loo"
    },
    {
      "short_description": "Arutor demo dec 5",
      "reason": "",
      "close_code": "",
      "closed_at": "",
      "backout_plan": "",
      "impact": "3 - Low",
      "description": "",
      "business_service": "",
      "type": "Emergency",
      "close_notes": "",
      "sys_id": "d52be87b97323110de1dfa67f053af08",
      "number": "CHG0030020",
      "opened_at": "2023-12-05 11:54:55",
      "sys_domain": "global",
      "state": "New",
      "justification": "",
      "sys_created_by": "abel.tuter",
      "assigned_to": ""
    },
    {
      "short_description": "Upgrade MySql 5.6 to 5.7",
      "reason": "",
      "close_code": "",
      "closed_at": "",
      "backout_plan": "",
      "impact": "3 - Low",
      "description": "Please upgrade existing MySql 5.6 to 5.7",
      "business_service": "",
      "type": "Emergency",
      "close_notes": "",
      "sys_id": "d53e72ec73d423002728660c4cf6a78d",
      "number": "CHG0002000",
      "opened_at": "2018-08-30 00:59:51",
      "sys_domain": "global",
      "state": "New",
      "justification": "",
      "sys_created_by": "admin",
      "assigned_to": ""
    },
    {
      "short_description": "Apply patches 10.2.0.1 to 10.2.0.3\n        ",
      "reason": "",
      "close_code": "",
      "closed_at": "",
      "backout_plan": " * Shut down the database\n            * Change Oracle Home to the old\n            one\n            * Start the database\n        ",
      "impact": "3 - Low",
      "description": "Need to apply the follow security patches from oracle -\n            10.2.0.1 to 10.2.0.3.\n        ",
      "business_service": "",
      "type": "Normal",
      "close_notes": "",
      "sys_id": "d7323e9dc0a8016700538974c2efb7f1",
      "number": "CHG0000009",
      "opened_at": "2023-07-18 22:07:53",
      "sys_domain": "global",
      "state": "New",
      "justification": "",
      "sys_created_by": "itil",
      "assigned_to": "Bow Ruggeri"
    },
    {
      "short_description": "Upgrade NY RAC to Oracle 12c",
      "reason": "",
      "close_code": "",
      "closed_at": "",
      "backout_plan": "Restore Oracle 11g binaries\nRestore Oracle 11g data files\nEnable Oracle Listener\nTest connectivity from PS LinuxApp01\nTest connectivity from PS LinuxApp02",
      "impact": "3 - Low",
      "description": "NY RAC instance needs to be upgraded from Oracle 11g to Oracle 12c",
      "business_service": "",
      "type": "Normal",
      "close_notes": "",
      "sys_id": "dacdb552db252200a6a2b31be0b8f5e7",
      "number": "CHG0000088",
      "opened_at": "2023-07-22 01:21:37",
      "sys_domain": "global",
      "state": "Authorize",
      "justification": "",
      "sys_created_by": "admin",
      "assigned_to": "Fred Luddy"
    },
    {
      "short_description": "Upgrade NY RAC to Oracle 12c",
      "reason": "",
      "close_code": "",
      "closed_at": "",
      "backout_plan": "Restore Oracle 11g binaries\nRestore Oracle 11g data files\nEnable Oracle Listener\nTest connectivity from PS LinuxApp01\nTest connectivity from PS LinuxApp02",
      "impact": "3 - Low",
      "description": "NY RAC instance needs to be upgraded from Oracle 11g to Oracle 12c",
      "business_service": "",
      "type": "Normal",
      "close_notes": "",
      "sys_id": "ddcdf152db252200a6a2b31be0b8f513",
      "number": "CHG0000048",
      "opened_at": "2023-07-22 01:21:32",
      "sys_domain": "global",
      "state": "Authorize",
      "justification": "",
      "sys_created_by": "admin",
      "assigned_to": "Fred Luddy"
    },
    {
      "short_description": "Change default router on unix201",
      "reason": "",
      "close_code": "",
      "closed_at": "",
      "backout_plan": "revert to default gateway 192.168.1.100\nRestart network with /etc/init.d/network restart\ntest network connectivity using ping 192.168.1.254\ntest network connectivity using ping 10.10.100.10",
      "impact": "3 - Low",
      "description": "",
      "business_service": "",
      "type": "Normal",
      "close_notes": "",
      "sys_id": "e2cdf552db252200a6a2b31be0b8f57f",
      "number": "CHG0000096",
      "opened_at": "2023-07-22 01:21:37",
      "sys_domain": "global",
      "state": "Authorize",
      "justification": "",
      "sys_created_by": "admin",
      "assigned_to": "David Loo"
    },
    {
      "short_description": "Update /etc/network/interfaces to include name servers 8.8.8.8 & 8.8.4.4",
      "reason": "",
      "close_code": "",
      "closed_at": "",
      "backout_plan": "Comment out new line in /etc/network/interfaces",
      "impact": "2 - Medium",
      "description": "We need to add additional redundant name servers to lnux100, lnux101 and PS LinuxApp01",
      "business_service": "",
      "type": "Normal",
      "close_notes": "",
      "sys_id": "e6cdf552db252200a6a2b31be0b8f533",
      "number": "CHG0000092",
      "opened_at": "2023-07-22 01:21:37",
      "sys_domain": "global",
      "state": "Authorize",
      "justification": "",
      "sys_created_by": "admin",
      "assigned_to": "Bow Ruggeri"
    },
    {
      "short_description": "Upgrade to Oracle 11i",
      "reason": "",
      "close_code": "",
      "closed_at": "2023-07-20 02:46:11",
      "backout_plan": "",
      "impact": "3 - Low",
      "description": "",
      "business_service": "",
      "type": "Normal",
      "close_notes": "",
      "sys_id": "e8f816d5c0a801640131b8101100744c",
      "number": "CHG0000004",
      "opened_at": "2021-06-13 08:31:06",
      "sys_domain": "global",
      "state": "Review",
      "justification": "",
      "sys_created_by": "admin",
      "assigned_to": "ITIL User"
    },
    {
      "short_description": "Upgrade OWA-SD-01 to MS Windows Server 2016",
      "reason": "",
      "close_code": "",
      "closed_at": "",
      "backout_plan": "re-image OWA-SD-01\nVerify network connectivity\nValidate OWA access using owa_test1 and owa_test2 test users\nFail from DR system back to OWA-SD-01",
      "impact": "2 - Medium",
      "description": "",
      "business_service": "",
      "type": "Normal",
      "close_notes": "",
      "sys_id": "eacdf552db252200a6a2b31be0b8f578",
      "number": "CHG0000095",
      "opened_at": "2023-07-22 01:21:37",
      "sys_domain": "global",
      "state": "Authorize",
      "justification": "",
      "sys_created_by": "admin",
      "assigned_to": "David Loo"
    },
    {
      "short_description": "Add network switch to cabinet",
      "reason": "",
      "close_code": "",
      "closed_at": "",
      "backout_plan": "-- Physically remove switch and all associated cabling\n-- Remove switch from management, monitoring and ServiceNow CMDB",
      "impact": "3 - Low",
      "description": "This standard change template describes adding a new network switch to a datacenter cabinet",
      "business_service": "",
      "type": "Standard",
      "close_notes": "",
      "sys_id": "eaf5d21347c12200e0ef563dbb9a7109",
      "number": "CHG0040002",
      "opened_at": "2016-08-10 09:09:51",
      "sys_domain": "global",
      "state": "New",
      "justification": "",
      "sys_created_by": "admin",
      "assigned_to": ""
    },
    {
      "short_description": "SGHUNG Dec. 5 Abel",
      "reason": "",
      "close_code": "",
      "closed_at": "",
      "backout_plan": "",
      "impact": "3 - Low",
      "description": "",
      "business_service": "",
      "type": "Normal",
      "close_notes": "",
      "sys_id": "ecea647b97323110de1dfa67f053af99",
      "number": "CHG0030019",
      "opened_at": "2023-12-05 11:53:46",
      "sys_domain": "global",
      "state": "New",
      "justification": "",
      "sys_created_by": "abel.tuter",
      "assigned_to": ""
    },
    {
      "short_description": "Update /etc/network/interfaces to include name servers 8.8.8.8 & 8.8.4.4",
      "reason": "",
      "close_code": "",
      "closed_at": "",
      "backout_plan": "Comment out new line in /etc/network/interfaces",
      "impact": "2 - Medium",
      "description": "We need to add additional redundant name servers to lnux100, lnux101 and PS LinuxApp01",
      "business_service": "",
      "type": "Normal",
      "close_notes": "",
      "sys_id": "eecdf552db252200a6a2b31be0b8f539",
      "number": "CHG0000093",
      "opened_at": "2023-07-22 01:21:37",
      "sys_domain": "global",
      "state": "Authorize",
      "justification": "",
      "sys_created_by": "admin",
      "assigned_to": "Bow Ruggeri"
    },
    {
      "short_description": "Upgrade NY RAC to Oracle 12c",
      "reason": "",
      "close_code": "",
      "closed_at": "",
      "backout_plan": "Restore Oracle 11g binaries\nRestore Oracle 11g data files\nEnable Oracle Listener\nTest connectivity from PS LinuxApp01\nTest connectivity from PS LinuxApp02",
      "impact": "3 - Low",
      "description": "NY RAC instance needs to be upgraded from Oracle 11g to Oracle 12c",
      "business_service": "",
      "type": "Normal",
      "close_notes": "",
      "sys_id": "f1cd7552db252200a6a2b31be0b8f523",
      "number": "CHG0000068",
      "opened_at": "2023-07-22 01:21:35",
      "sys_domain": "global",
      "state": "Authorize",
      "justification": "",
      "sys_created_by": "admin",
      "assigned_to": "Fred Luddy"
    },
    {
      "short_description": "Sept 14 testing",
      "reason": "",
      "close_code": "",
      "closed_at": "",
      "backout_plan": "",
      "impact": "3 - Low",
      "description": "",
      "business_service": "",
      "type": "Normal",
      "close_notes": "",
      "sys_id": "f2ba2a9997953110de1dfa67f053af3c",
      "number": "CHG0030007",
      "opened_at": "2023-09-14 14:13:21",
      "sys_domain": "global",
      "state": "New",
      "justification": "",
      "sys_created_by": "abel.tuter",
      "assigned_to": ""
    },
    {
      "short_description": "Dec 5",
      "reason": "",
      "close_code": "Unsuccessful",
      "closed_at": "",
      "backout_plan": "",
      "impact": "3 - Low",
      "description": "Testing",
      "business_service": "",
      "type": "Emergency",
      "close_notes": "Couldn't setup server",
      "sys_id": "f4f8ecb797323110de1dfa67f053af71",
      "number": "CHG0030018",
      "opened_at": "2023-12-05 11:45:19",
      "sys_domain": "global",
      "state": "New",
      "justification": "",
      "sys_created_by": "admin",
      "assigned_to": ""
    },
    {
      "short_description": "Increase db_block_buffers from 5000 to 7500",
      "reason": "",
      "close_code": "",
      "closed_at": "",
      "backout_plan": "rollback to existing db_block_buffer setting",
      "impact": "2 - Medium",
      "description": "The database size has increased and the cache hit rate is at the low end of an acceptable rate. The Database team needss to increase the amount of memory allocated to the Oracle SGA to increase the cache hit rate.",
      "business_service": "",
      "type": "Normal",
      "close_notes": "",
      "sys_id": "f5cd3552db252200a6a2b31be0b8f5b2",
      "number": "CHG0000064",
      "opened_at": "2023-07-22 01:21:34",
      "sys_domain": "global",
      "state": "Authorize",
      "justification": "",
      "sys_created_by": "admin",
      "assigned_to": "David Loo"
    },
    {
      "short_description": "Server was shutdown",
      "reason": "",
      "close_code": "Unsuccessful",
      "closed_at": "",
      "backout_plan": "",
      "impact": "3 - Low",
      "description": "Server shutdown and is offline",
      "business_service": "",
      "type": "Normal",
      "close_notes": "Had problems shutting off server",
      "sys_id": "f6268c3897997110de1dfa67f053af7a",
      "number": "CHG0030001",
      "opened_at": "2023-09-12 12:57:24",
      "sys_domain": "global",
      "state": "Implement",
      "justification": "",
      "sys_created_by": "admin",
      "assigned_to": ""
    },
    {
      "short_description": "Update /etc/network/interfaces to include name servers 8.8.8.8 & 8.8.4.4",
      "reason": "",
      "close_code": "",
      "closed_at": "",
      "backout_plan": "Comment out new line in /etc/network/interfaces",
      "impact": "2 - Medium",
      "description": "We need to add additional redundant name servers to lnux100, lnux101 and PS LinuxApp01",
      "business_service": "",
      "type": "Normal",
      "close_notes": "",
      "sys_id": "fdcd3552db252200a6a2b31be0b8f5ab",
      "number": "CHG0000063",
      "opened_at": "2023-07-22 01:21:34",
      "sys_domain": "global",
      "state": "Authorize",
      "justification": "",
      "sys_created_by": "admin",
      "assigned_to": "Bow Ruggeri"
    }
  ]